<?xml version="1.0" encoding="UTF-8"?>
<launch4jConfig>
  <dontWrapJar>false</dontWrapJar>
  <headerType>gui</headerType>
  <jar>C:\Users\Artur\Desktop\_F_I_N_A_L_\!Windows Builder\Sources\FishRespBase.jar</jar>
  <outfile>C:\Users\Artur\Desktop\_F_I_N_A_L_\!Windows Builder\Sources\FishResp.exe</outfile>
  <errTitle></errTitle>
  <cmdLine></cmdLine>
  <chdir>.</chdir>
  <priority>high</priority>
  <downloadUrl>http://java.com/download</downloadUrl>
  <supportUrl></supportUrl>
  <stayAlive>true</stayAlive>
  <restartOnCrash>false</restartOnCrash>
  <manifest></manifest>
  <icon>C:\Users\Artur\Desktop\_F_I_N_A_L_\programIcon.ico</icon>
  <jre>
    <path></path>
    <bundledJre64Bit>false</bundledJre64Bit>
    <bundledJreAsFallback>false</bundledJreAsFallback>
    <minVersion>1.8.0</minVersion>
    <maxVersion></maxVersion>
    <jdkPreference>preferJre</jdkPreference>
    <runtimeBits>64</runtimeBits>
  </jre>
</launch4jConfig>